MP2/pwm.sv
module pwm (
    input   logic       clk,
    input   logic [7:0] duty,
    output  logic       on
);

    logic [7:0] pwm_count = 0;
    always_ff @(posedge clk) begin
        if (pwm_count == 8'd249)
            pwm_count <= 8'd0;
        else
            pwm_count <= pwm_count + 1; 
    end

    assign on = pwm_count < duty;

endmodule

MP2/color_cycle.sv
module color_cycle (
    input logic clk,
    output logic [7:0] red_duty,
    output logic [7:0] green_duty,
    output logic [7:0] blue_duty
);

    localparam int CLOCKS_PER_STEP = 8000;
    localparam int STEPS_PER_SECTOR = 250;
    localparam int NUM_SECTORS = 6;

    logic [$clog2(CLOCKS_PER_STEP)-1 : 0] tick_count = 0;
    logic [$clog2(STEPS_PER_SECTOR)-1 : 0] step = 0;
    logic [$clog2(NUM_SECTORS)-1 : 0] sector = 0;

    always_ff @(posedge clk) begin
        if (tick_count == CLOCKS_PER_STEP - 1) begin
            tick_count <= 0;
            if (step == STEPS_PER_SECTOR - 1) begin
                step <= 0;
                if (sector == NUM_SECTORS - 1) begin
                    sector <= 0;
                end else
                    sector <= sector + 1;
            end else
                step <= step + 1;
        end else
            tick_count <= tick_count + 1;
    end

    always_comb begin
        red_duty = 8'd0;
        green_duty = 8'd0;
        blue_duty = 8'd0;

        case (sector)
            3'd0: begin
                red_duty   = 8'd250;
                green_duty = step;
            end
            3'd1: begin
                red_duty   = 8'd250 - step;
                green_duty = 8'd250;
            end
            3'd2: begin
                green_duty   = 8'd250;
                blue_duty = step;
            end
            3'd3: begin
                green_duty   = 8'd250 - step;
                blue_duty = 8'd250;
            end
            3'd4: begin
                blue_duty   = 8'd250;
                red_duty = step;
            end
            3'd5: begin
                blue_duty   = 8'd250 - step;
                red_duty = 8'd250;
            end
        endcase
    end
endmodule

MP2/top.sv
module top (
    input  logic clk,
    output logic RGB_R,
    output logic RGB_G,
    output logic RGB_B
);
    logic [7:0] red_duty, green_duty, blue_duty;
    logic red_on, green_on, blue_on;

    color_cycle colors (
        .clk(clk),
        .red_duty(red_duty),
        .green_duty(green_duty),
        .blue_duty(blue_duty)
    );

    pwm red_pwm (
        .clk(clk),
        .duty(red_duty),
        .on(red_on)
    );

    pwm green_pwm (
        .clk(clk),
        .duty(green_duty),
        .on(green_on)
    );

    pwm blue_pwm (
        .clk(clk),
        .duty(blue_duty),
        .on(blue_on)
    );
    

    assign RGB_R = ~red_on;
    assign RGB_G = ~green_on;
    assign RGB_B = ~blue_on;
    
endmodule

MP2/mp2_tb.sv
`timescale 1ns/1ps
module mp2_tb;
    localparam int CYCLES_TO_SIMULATE = 3;
    localparam int CLOCKS_PER_CYCLE = 12_000_000;

    logic clk = 0;
    logic RGB_R, RGB_G, RGB_B;

    always #41.667 clk = ~clk;

    top u0 (
        .clk(clk),
        .RGB_R(RGB_R),
        .RGB_G(RGB_G),
        .RGB_B(RGB_B)
    );

    initial begin
        $dumpfile("mp2.vcd");
        $dumpvars(0, u0.red_duty, u0.green_duty, u0.blue_duty);

        repeat (CYCLES_TO_SIMULATE * CLOCKS_PER_CYCLE + 1) @(posedge clk);
        $finish;
    end
endmodule

MP2/mp2.vcd
$date
	Mon Sep 28 17:52:09 2026
$end
$version
	Icarus Verilog
$end
$timescale
	1ps
$end
$scope module mp2_tb $end
$scope module u0 $end
$var wire 8 ! red_duty [7:0] $end
$upscope $end
$upscope $end
$scope module mp2_tb $end
$scope module u0 $end
$var wire 8 " green_duty [7:0] $end
$upscope $end
$upscope $end
$scope module mp2_tb $end
$scope module u0 $end
$var wire 8 # blue_duty [7:0] $end
$upscope $end
$upscope $end
$enddefinitions $end
$comment Show the parameter values. $end
$dumpall
$end
#0
$dumpvars
b0 #
b0 "
b11111010 !
$end
#666630333
b1 "
b11111010 !
#1333302333
b10 "
b11111010 !
#1999974333
b11 "
b11111010 !
#2666646333
b100 "
b11111010 !
#3333318333
b101 "
b11111010 !
#3999990333
b110 "
b11111010 !
#4666662333
b111 "
b11111010 !
#5333334333
b1000 "
b11111010 !
#6000006333
b1001 "
b11111010 !
#6666678333
b1010 "
b11111010 !
#7333350333
b1011 "
b11111010 !
#8000022333
b1100 "
b11111010 !
#8666694333
b1101 "
b11111010 !
#9333366333
b1110 "
b11111010 !
#10000038333
b1111 "
b11111010 !
#10666710333
b10000 "
b11111010 !
#11333382333
b10001 "
b11111010 !
#12000054333
b10010 "
b11111010 !
#12666726333
b10011 "
b11111010 !
#13333398333
b10100 "
b11111010 !
#14000070333
b10101 "
b11111010 !
#14666742333
b10110 "
b11111010 !
#15333414333
b10111 "
b11111010 !
#16000086333
b11000 "
b11111010 !
#16666758333
b11001 "
b11111010 !
#17333430333
b11010 "
b11111010 !
#18000102333
b11011 "
b11111010 !
#18666774333
b11100 "
b11111010 !
#19333446333
b11101 "
b11111010 !
#20000118333
b11110 "
b11111010 !
#20666790333
b11111 "
b11111010 !
#21333462333
b100000 "
b11111010 !
#22000134333
b100001 "
b11111010 !
#22666806333
b100010 "
b11111010 !
#23333478333
b100011 "
b11111010 !
#24000150333
b100100 "
b11111010 !
#24666822333
b100101 "
b11111010 !
#25333494333
b100110 "
b11111010 !
#26000166333
b100111 "
b11111010 !
#26666838333
b101000 "
b11111010 !
#27333510333
b101001 "
b11111010 !
#28000182333
b101010 "
b11111010 !
#28666854333
b101011 "
b11111010 !
#29333526333
b101100 "
b11111010 !
#30000198333
b101101 "
b11111010 !
#30666870333
b101110 "
b11111010 !
#31333542333
b101111 "
b11111010 !
#32000214333
b110000 "
b11111010 !
#32666886333
b110001 "
b11111010 !
#33333558333
b110010 "
b11111010 !
#34000230333
b110011 "
b11111010 !
#34666902333
b110100 "
b11111010 !
#35333574333
b110101 "
b11111010 !
#36000246333
b110110 "
b11111010 !
#36666918333
b110111 "
b11111010 !
#37333590333
b111000 "
b11111010 !
#38000262333
b111001 "
b11111010 !
#38666934333
b111010 "
b11111010 !
#39333606333
b111011 "
b11111010 !
#40000278333
b111100 "
b11111010 !
#40666950333
b111101 "
b11111010 !
#41333622333
b111110 "
b11111010 !
#42000294333
b111111 "
b11111010 !
#42666966333
b1000000 "
b11111010 !
#43333638333
b1000001 "
b11111010 !
#44000310333
b1000010 "
b11111010 !
#44666982333
b1000011 "
b11111010 !
#45333654333
b1000100 "
b11111010 !
#46000326333
b1000101 "
b11111010 !
#46666998333
b1000110 "
b11111010 !
#47333670333
b1000111 "
b11111010 !
#48000342333
b1001000 "
b11111010 !
#48667014333
b1001001 "
b11111010 !
#49333686333
b1001010 "
b11111010 !
#50000358333
b1001011 "
b11111010 !
#50667030333
b1001100 "
b11111010 !
#51333702333
b1001101 "
b11111010 !
#52000374333
b1001110 "
b11111010 !
#52667046333
b1001111 "
b11111010 !
#53333718333
b1010000 "
b11111010 !
#54000390333
b1010001 "
b11111010 !
#54667062333
b1010010 "
b11111010 !
#55333734333
b1010011 "
b11111010 !
#56000406333
b1010100 "
b11111010 !
#56667078333
b1010101 "
b11111010 !
#57333750333
b1010110 "
b11111010 !
#58000422333
b1010111 "
b11111010 !
#58667094333
b1011000 "
b11111010 !
#59333766333
b1011001 "
b11111010 !
#60000438333
b1011010 "
b11111010 !
#60667110333
b1011011 "
b11111010 !
#61333782333
b1011100 "
b11111010 !
#62000454333
b1011101 "
b11111010 !
#62667126333
b1011110 "
b11111010 !
#63333798333
b1011111 "
b11111010 !
#64000470333
b1100000 "
b11111010 !
#64667142333
b1100001 "
b11111010 !
#65333814333
b1100010 "
b11111010 !
#66000486333
b1100011 "
b11111010 !
#66667158333
b1100100 "
b11111010 !
#67333830333
b1100101 "
b11111010 !
#68000502333
b1100110 "
b11111010 !
#68667174333
b1100111 "
b11111010 !
#69333846333
b1101000 "
b11111010 !
#70000518333
b1101001 "
b11111010 !
#70667190333
b1101010 "
b11111010 !
#71333862333
b1101011 "
b11111010 !
#72000534333
b1101100 "
b11111010 !
#72667206333
b1101101 "
b11111010 !
#73333878333
b1101110 "
b11111010 !
#74000550333
b1101111 "
b11111010 !
#74667222333
b1110000 "
b11111010 !
#75333894333
b1110001 "
b11111010 !
#76000566333
b1110010 "
b11111010 !
#76667238333
b1110011 "
b11111010 !
#77333910333
b1110100 "
b11111010 !
#78000582333
b1110101 "
b11111010 !
#78667254333
b1110110 "
b11111010 !
#79333926333
b1110111 "
b11111010 !
#80000598333
b1111000 "
b11111010 !
#80667270333
b1111001 "
b11111010 !
#81333942333
b1111010 "
b11111010 !
#82000614333
b1111011 "
b11111010 !
#82667286333
b1111100 "
b11111010 !
#83333958333
b1111101 "
b11111010 !
#84000630333
b1111110 "
b11111010 !
#84667302333
b1111111 "
b11111010 !
#85333974333
b10000000 "
b11111010 !
#86000646333
b10000001 "
b11111010 !
#86667318333
b10000010 "
b11111010 !
#87333990333
b10000011 "
b11111010 !
#88000662333
b10000100 "
b11111010 !
#88667334333
b10000101 "
b11111010 !
#89334006333
b10000110 "
b11111010 !
#90000678333
b10000111 "
b11111010 !
#90667350333
b10001000 "
b11111010 !
#91334022333
b10001001 "
b11111010 !
#92000694333
b10001010 "
b11111010 !
#92667366333
b10001011 "
b11111010 !
#93334038333
b10001100 "
b11111010 !
#94000710333
b10001101 "
b11111010 !
#94667382333
b10001110 "
b11111010 !
#95334054333
b10001111 "
b11111010 !
#96000726333
b10010000 "
b11111010 !
#96667398333
b10010001 "
b11111010 !
#97334070333
b10010010 "
b11111010 !
#98000742333
b10010011 "
b11111010 !
#98667414333
b10010100 "
b11111010 !
#99334086333
b10010101 "
b11111010 !
#100000758333
b10010110 "
b11111010 !
#100667430333
b10010111 "
b11111010 !
#101334102333
b10011000 "
b11111010 !
#102000774333
b10011001 "
b11111010 !
#102667446333
b10011010 "
b11111010 !
#103334118333
b10011011 "
b11111010 !
#104000790333
b10011100 "
b11111010 !
#104667462333
b10011101 "
b11111010 !
#105334134333
b10011110 "
b11111010 !
#106000806333
b10011111 "
b11111010 !
#106667478333
b10100000 "
b11111010 !
#107334150333
b10100001 "
b11111010 !
#108000822333
b10100010 "
b11111010 !
#108667494333
b10100011 "
b11111010 !
#109334166333
b10100100 "
b11111010 !
#110000838333
b10100101 "
b11111010 !
#110667510333
b10100110 "
b11111010 !
#111334182333
b10100111 "
b11111010 !
#112000854333
b10101000 "
b11111010 !
#112667526333
b10101001 "
b11111010 !
#113334198333
b10101010 "
b11111010 !
#114000870333
b10101011 "
b11111010 !
#114667542333
b10101100 "
b11111010 !
#115334214333
b10101101 "
b11111010 !
#116000886333
b10101110 "
b11111010 !
#116667558333
b10101111 "
b11111010 !
#117334230333
b10110000 "
b11111010 !
#118000902333
b10110001 "
b11111010 !
#118667574333
b10110010 "
b11111010 !
#119334246333
b10110011 "
b11111010 !
#120000918333
b10110100 "
b11111010 !
#120667590333
b10110101 "
b11111010 !
#121334262333
b10110110 "
b11111010 !
#122000934333
b10110111 "
b11111010 !
#122667606333
b10111000 "
b11111010 !
#123334278333
b10111001 "
b11111010 !
#124000950333
b10111010 "
b11111010 !
#124667622333
b10111011 "
b11111010 !
#125334294333
b10111100 "
b11111010 !
#126000966333
b10111101 "
b11111010 !
#126667638333
b10111110 "
b11111010 !
#127334310333
b10111111 "
b11111010 !
#128000982333
b11000000 "
b11111010 !
#128667654333
b11000001 "
b11111010 !
#129334326333
b11000010 "
b11111010 !
#130000998333
b11000011 "
b11111010 !
#130667670333
b11000100 "
b11111010 !
#131334342333
b11000101 "
b11111010 !
#132001014333
b11000110 "
b11111010 !
#132667686333
b11000111 "
b11111010 !
#133334358333
b11001000 "
b11111010 !
#134001030333
b11001001 "
b11111010 !
#134667702333
b11001010 "
b11111010 !
#135334374333
b11001011 "
b11111010 !
#136001046333
b11001100 "
b11111010 !
#136667718333
b11001101 "
b11111010 !
#137334390333
b11001110 "
b11111010 !
#138001062333
b11001111 "
b11111010 !
#138667734333
b11010000 "
b11111010 !
#139334406333
b11010001 "
b11111010 !
#140001078333
b11010010 "
b11111010 !
#140667750333
b11010011 "
b11111010 !
#141334422333
b11010100 "
b11111010 !
#142001094333
b11010101 "
b11111010 !
#142667766333
b11010110 "
b11111010 !
#143334438333
b11010111 "
b11111010 !
#144001110333
b11011000 "
b11111010 !
#144667782333
b11011001 "
b11111010 !
#145334454333
b11011010 "
b11111010 !
#146001126333
b11011011 "
b11111010 !
#146667798333
b11011100 "
b11111010 !
#147334470333
b11011101 "
b11111010 !
#148001142333
b11011110 "
b11111010 !
#148667814333
b11011111 "
b11111010 !
#149334486333
b11100000 "
b11111010 !
#150001158333
b11100001 "
b11111010 !
#150667830333
b11100010 "
b11111010 !
#151334502333
b11100011 "
b11111010 !
#152001174333
b11100100 "
b11111010 !
#152667846333
b11100101 "
b11111010 !
#153334518333
b11100110 "
b11111010 !
#154001190333
b11100111 "
b11111010 !
#154667862333
b11101000 "
b11111010 !
#155334534333
b11101001 "
b11111010 !
#156001206333
b11101010 "
b11111010 !
#156667878333
b11101011 "
b11111010 !
#157334550333
b11101100 "
b11111010 !
#158001222333
b11101101 "
b11111010 !
#158667894333
b11101110 "
b11111010 !
#159334566333
b11101111 "
b11111010 !
#160001238333
b11110000 "
b11111010 !
#160667910333
b11110001 "
b11111010 !
#161334582333
b11110010 "
b11111010 !
#162001254333
b11110011 "
b11111010 !
#162667926333
b11110100 "
b11111010 !
#163334598333
b11110101 "
b11111010 !
#164001270333
b11110110 "
b11111010 !
#164667942333
b11110111 "
b11111010 !
#165334614333
b11111000 "
b11111010 !
#166001286333
b11111001 "
b11111010 !
#166667958333
b11111010 "
b11111010 !
#167334630333
b11111010 "
b11111001 !
#168001302333
b11111010 "
b11111000 !
#168667974333
b11111010 "
b11110111 !
#169334646333
b11111010 "
b11110110 !
#170001318333
b11111010 "
b11110101 !
#170667990333
b11111010 "
b11110100 !
#171334662333
b11111010 "
b11110011 !
#172001334333
b11111010 "
b11110010 !
#172668006333
b11111010 "
b11110001 !
#173334678333
b11111010 "
b11110000 !
#174001350333
b11111010 "
b11101111 !
#174668022333
b11111010 "
b11101110 !
#175334694333
b11111010 "
b11101101 !
#176001366333
b11111010 "
b11101100 !
#176668038333
b11111010 "
b11101011 !
#177334710333
b11111010 "
b11101010 !
#178001382333
b11111010 "
b11101001 !
#178668054333
b11111010 "
b11101000 !
#179334726333
b11111010 "
b11100111 !
#180001398333
b11111010 "
b11100110 !
#180668070333
b11111010 "
b11100101 !
#181334742333
b11111010 "
b11100100 !
#182001414333
b11111010 "
b11100011 !
#182668086333
b11111010 "
b11100010 !
#183334758333
b11111010 "
b11100001 !
#184001430333
b11111010 "
b11100000 !
#184668102333
b11111010 "
b11011111 !
#185334774333
b11111010 "
b11011110 !
#186001446333
b11111010 "
b11011101 !
#186668118333
b11111010 "
b11011100 !
#187334790333
b11111010 "
b11011011 !
#188001462333
b11111010 "
b11011010 !
#188668134333
b11111010 "
b11011001 !
#189334806333
b11111010 "
b11011000 !
#190001478333
b11111010 "
b11010111 !
#190668150333
b11111010 "
b11010110 !
#191334822333
b11111010 "
b11010101 !
#192001494333
b11111010 "
b11010100 !
#192668166333
b11111010 "
b11010011 !
#193334838333
b11111010 "
b11010010 !
#194001510333
b11111010 "
b11010001 !
#194668182333
b11111010 "
b11010000 !
#195334854333
b11111010 "
b11001111 !
#196001526333
b11111010 "
b11001110 !
#196668198333
b11111010 "
b11001101 !
#197334870333
b11111010 "
b11001100 !
#198001542333
b11111010 "
b11001011 !
#198668214333
b11111010 "
b11001010 !
#199334886333
b11111010 "
b11001001 !
#200001558333
b11111010 "
b11001000 !
#200668230333
b11111010 "
b11000111 !
#201334902333
b11111010 "
b11000110 !
#202001574333
b11111010 "
b11000101 !
#202668246333
b11111010 "
b11000100 !
#203334918333
b11111010 "
b11000011 !
#204001590333
b11111010 "
b11000010 !
#204668262333
b11111010 "
b11000001 !
#205334934333
b11111010 "
b11000000 !
#206001606333
b11111010 "
b10111111 !
#206668278333
b11111010 "
b10111110 !
#207334950333
b11111010 "
b10111101 !
#208001622333
b11111010 "
b10111100 !
#208668294333
b11111010 "
b10111011 !
#209334966333
b11111010 "
b10111010 !
#210001638333
b11111010 "
b10111001 !
#210668310333
b11111010 "
b10111000 !
#211334982333
b11111010 "
b10110111 !
#212001654333
b11111010 "
b10110110 !
#212668326333
b11111010 "
b10110101 !
#213334998333
b11111010 "
b10110100 !
#214001670333
b11111010 "
b10110011 !
#214668342333
b11111010 "
b10110010 !
#215335014333
b11111010 "
b10110001 !
#216001686333
b11111010 "
b10110000 !
#216668358333
b11111010 "
b10101111 !
#217335030333
b11111010 "
b10101110 !
#218001702333
b11111010 "
b10101101 !
#218668374333
b11111010 "
b10101100 !
#219335046333
b11111010 "
b10101011 !
#220001718333
b11111010 "
b10101010 !
#220668390333
b11111010 "
b10101001 !
#221335062333
b11111010 "
b10101000 !
#222001734333
b11111010 "
b10100111 !
#222668406333
b11111010 "
b10100110 !
#223335078333
b11111010 "
b10100101 !
#224001750333
b11111010 "
b10100100 !
#224668422333
b11111010 "
b10100011 !
#225335094333
b11111010 "
b10100010 !
#226001766333
b11111010 "
b10100001 !
#226668438333
b11111010 "
b10100000 !
#227335110333
b11111010 "
b10011111 !
#228001782333
b11111010 "
b10011110 !
#228668454333
b11111010 "
b10011101 !
#229335126333
b11111010 "
b10011100 !
#230001798333
b11111010 "
b10011011 !
#230668470333
b11111010 "
b10011010 !
#231335142333
b11111010 "
b10011001 !
#232001814333
b11111010 "
b10011000 !
#232668486333
b11111010 "
b10010111 !
#233335158333
b11111010 "
b10010110 !
#234001830333
b11111010 "
b10010101 !
#234668502333
b11111010 "
b10010100 !
#235335174333
b11111010 "
b10010011 !
#236001846333
b11111010 "
b10010010 !
#236668518333
b11111010 "
b10010001 !
#237335190333
b11111010 "
b10010000 !
#238001862333
b11111010 "
b10001111 !
#238668534333
b11111010 "
b10001110 !
#239335206333
b11111010 "
b10001101 !
#240001878333
b11111010 "
b10001100 !
#240668550333
b11111010 "
b10001011 !
#241335222333
b11111010 "
b10001010 !
#242001894333
b11111010 "
b10001001 !
#242668566333
b11111010 "
b10001000 !
#243335238333
b11111010 "
b10000111 !
#244001910333
b11111010 "
b10000110 !
#244668582333
b11111010 "
b10000101 !
#245335254333
b11111010 "
b10000100 !
#246001926333
b11111010 "
b10000011 !
#246668598333
b11111010 "
b10000010 !
#247335270333
b11111010 "
b10000001 !
#248001942333
b11111010 "
b10000000 !
#248668614333
b11111010 "
b1111111 !
#249335286333
b11111010 "
b1111110 !
#250001958333
b11111010 "
b1111101 !
#250668630333
b11111010 "
b1111100 !
#251335302333
b11111010 "
b1111011 !
#252001974333
b11111010 "
b1111010 !
#252668646333
b11111010 "
b1111001 !
#253335318333
b11111010 "
b1111000 !
#254001990333
b11111010 "
b1110111 !
#254668662333
b11111010 "
b1110110 !
#255335334333
b11111010 "
b1110101 !
#256002006333
b11111010 "
b1110100 !
#256668678333
b11111010 "
b1110011 !
#257335350333
b11111010 "
b1110010 !
#258002022333
b11111010 "
b1110001 !
#258668694333
b11111010 "
b1110000 !
#259335366333
b11111010 "
b1101111 !
#260002038333
b11111010 "
b1101110 !
#260668710333
b11111010 "
b1101101 !
#261335382333
b11111010 "
b1101100 !
#262002054333
b11111010 "
b1101011 !
#262668726333
b11111010 "
b1101010 !
#263335398333
b11111010 "
b1101001 !
#264002070333
b11111010 "
b1101000 !
#264668742333
b11111010 "
b1100111 !
#265335414333
b11111010 "
b1100110 !
#266002086333
b11111010 "
b1100101 !
#266668758333
b11111010 "
b1100100 !
#267335430333
b11111010 "
b1100011 !
#268002102333
b11111010 "
b1100010 !
#268668774333
b11111010 "
b1100001 !
#269335446333
b11111010 "
b1100000 !
#270002118333
b11111010 "
b1011111 !
#270668790333
b11111010 "
b1011110 !
#271335462333
b11111010 "
b1011101 !
#272002134333
b11111010 "
b1011100 !
#272668806333
b11111010 "
b1011011 !
#273335478333
b11111010 "
b1011010 !
#274002150333
b11111010 "
b1011001 !
#274668822333
b11111010 "
b1011000 !
#275335494333
b11111010 "
b1010111 !
#276002166333
b11111010 "
b1010110 !
#276668838333
b11111010 "
b1010101 !
#277335510333
b11111010 "
b1010100 !
#278002182333
b11111010 "
b1010011 !
#278668854333
b11111010 "
b1010010 !
#279335526333
b11111010 "
b1010001 !
#280002198333
b11111010 "
b1010000 !
#280668870333
b11111010 "
b1001111 !
#281335542333
b11111010 "
b1001110 !
#282002214333
b11111010 "
b1001101 !
#282668886333
b11111010 "
b1001100 !
#283335558333
b11111010 "
b1001011 !
#284002230333
b11111010 "
b1001010 !
#284668902333
b11111010 "
b1001001 !
#285335574333
b11111010 "
b1001000 !
#286002246333
b11111010 "
b1000111 !
#286668918333
b11111010 "
b1000110 !
#287335590333
b11111010 "
b1000101 !
#288002262333
b11111010 "
b1000100 !
#288668934333
b11111010 "
b1000011 !
#289335606333
b11111010 "
b1000010 !
#290002278333
b11111010 "
b1000001 !
#290668950333
b11111010 "
b1000000 !
#291335622333
b11111010 "
b111111 !
#292002294333
b11111010 "
b111110 !
#292668966333
b11111010 "
b111101 !
#293335638333
b11111010 "
b111100 !
#294002310333
b11111010 "
b111011 !
#294668982333
b11111010 "
b111010 !
#295335654333
b11111010 "
b111001 !
#296002326333
b11111010 "
b111000 !
#296668998333
b11111010 "
b110111 !
#297335670333
b11111010 "
b110110 !
#298002342333
b11111010 "
b110101 !
#298669014333
b11111010 "
b110100 !
#299335686333
b11111010 "
b110011 !
#300002358333
b11111010 "
b110010 !
#300669030333
b11111010 "
b110001 !
#301335702333
b11111010 "
b110000 !
#302002374333
b11111010 "
b101111 !
#302669046333
b11111010 "
b101110 !
#303335718333
b11111010 "
b101101 !
#304002390333
b11111010 "
b101100 !
#304669062333
b11111010 "
b101011 !
#305335734333
b11111010 "
b101010 !
#306002406333
b11111010 "
b101001 !
#306669078333
b11111010 "
b101000 !
#307335750333
b11111010 "
b100111 !
#308002422333
b11111010 "
b100110 !
#308669094333
b11111010 "
b100101 !
#309335766333
b11111010 "
b100100 !
#310002438333
b11111010 "
b100011 !
#310669110333
b11111010 "
b100010 !
#311335782333
b11111010 "
b100001 !
#312002454333
b11111010 "
b100000 !
#312669126333
b11111010 "
b11111 !
#313335798333
b11111010 "
b11110 !
#314002470333
b11111010 "
b11101 !
#314669142333
b11111010 "
b11100 !
#315335814333
b11111010 "
b11011 !
#316002486333
b11111010 "
b11010 !
#316669158333
b11111010 "
b11001 !
#317335830333
b11111010 "
b11000 !
#318002502333
b11111010 "
b10111 !
#318669174333
b11111010 "
b10110 !
#319335846333
b11111010 "
b10101 !
#320002518333
b11111010 "
b10100 !
#320669190333
b11111010 "
b10011 !
#321335862333
b11111010 "
b10010 !
#322002534333
b11111010 "
b10001 !
#322669206333
b11111010 "
b10000 !
#323335878333
b11111010 "
b1111 !
#324002550333
b11111010 "
b1110 !
#324669222333
b11111010 "
b1101 !
#325335894333
b11111010 "
b1100 !
#326002566333
b11111010 "
b1011 !
#326669238333
b11111010 "
b1010 !
#327335910333
b11111010 "
b1001 !
#328002582333
b11111010 "
b1000 !
#328669254333
b11111010 "
b111 !
#329335926333
b11111010 "
b110 !
#330002598333
b11111010 "
b101 !
#330669270333
b11111010 "
b100 !
#331335942333
b11111010 "
b11 !
#332002614333
b11111010 "
b10 !
#332669286333
b11111010 "
b1 !
#333335958333
b11111010 "
b0 !
#334002630333
b1 #
b11111010 "
#334669302333
b10 #
b11111010 "
#335335974333
b11 #
b11111010 "
#336002646333
b100 #
b11111010 "
#336669318333
b101 #
b11111010 "
#337335990333
b110 #
b11111010 "
#338002662333
b111 #
b11111010 "
#338669334333
b1000 #
b11111010 "
#339336006333
b1001 #
b11111010 "
#340002678333
b1010 #
b11111010 "
#340669350333
b1011 #
b11111010 "
#341336022333
b1100 #
b11111010 "
#342002694333
b1101 #
b11111010 "
#342669366333
b1110 #
b11111010 "
#343336038333
b1111 #
b11111010 "
#344002710333
b10000 #
b11111010 "
#344669382333
b10001 #
b11111010 "
#345336054333
b10010 #
b11111010 "
#346002726333
b10011 #
b11111010 "
#346669398333
b10100 #
b11111010 "
#347336070333
b10101 #
b11111010 "
#348002742333
b10110 #
b11111010 "
#348669414333
b10111 #
b11111010 "
#349336086333
b11000 #
b11111010 "
#350002758333
b11001 #
b11111010 "
#350669430333
b11010 #
b11111010 "
#351336102333
b11011 #
b11111010 "
#352002774333
b11100 #
b11111010 "
#352669446333
b11101 #
b11111010 "
#353336118333
b11110 #
b11111010 "
#354002790333
b11111 #
b11111010 "
#354669462333
b100000 #
b11111010 "
#355336134333
b100001 #
b11111010 "
#356002806333
b100010 #
b11111010 "
#356669478333
b100011 #
b11111010 "
#357336150333
b100100 #
b11111010 "
#358002822333
b100101 #
b11111010 "
#358669494333
b100110 #
b11111010 "
#359336166333
b100111 #
b11111010 "
#360002838333
b101000 #
b11111010 "
#360669510333
b101001 #
b11111010 "
#361336182333
b101010 #
b11111010 "
#362002854333
b101011 #
b11111010 "
#362669526333
b101100 #
b11111010 "
#363336198333
b101101 #
b11111010 "
#364002870333
b101110 #
b11111010 "
#364669542333
b101111 #
b11111010 "
#365336214333
b110000 #
b11111010 "
#366002886333
b110001 #
b11111010 "
#366669558333
b110010 #
b11111010 "
#367336230333
b110011 #
b11111010 "
#368002902333
b110100 #
b11111010 "
#368669574333
b110101 #
b11111010 "
#369336246333
b110110 #
b11111010 "
#370002918333
b110111 #
b11111010 "
#370669590333
b111000 #
b11111010 "
#371336262333
b111001 #
b11111010 "
#372002934333
b111010 #
b11111010 "
#372669606333
b111011 #
b11111010 "
#373336278333
b111100 #
b11111010 "
#374002950333
b111101 #
b11111010 "
#374669622333
b111110 #
b11111010 "
#375336294333
b111111 #
b11111010 "
#376002966333
b1000000 #
b11111010 "
#376669638333
b1000001 #
b11111010 "
#377336310333
b1000010 #
b11111010 "
#378002982333
b1000011 #
b11111010 "
#378669654333
b1000100 #
b11111010 "
#379336326333
b1000101 #
b11111010 "
#380002998333
b1000110 #
b11111010 "
#380669670333
b1000111 #
b11111010 "
#381336342333
b1001000 #
b11111010 "
#382003014333
b1001001 #
b11111010 "
#382669686333
b1001010 #
b11111010 "
#383336358333
b1001011 #
b11111010 "
#384003030333
b1001100 #
b11111010 "
#384669702333
b1001101 #
b11111010 "
#385336374333
b1001110 #
b11111010 "
#386003046333
b1001111 #
b11111010 "
#386669718333
b1010000 #
b11111010 "
#387336390333
b1010001 #
b11111010 "
#388003062333
b1010010 #
b11111010 "
#388669734333
b1010011 #
b11111010 "
#389336406333
b1010100 #
b11111010 "
#390003078333
b1010101 #
b11111010 "
#390669750333
b1010110 #
b11111010 "
#391336422333
b1010111 #
b11111010 "
#392003094333
b1011000 #
b11111010 "
#392669766333
b1011001 #
b11111010 "
#393336438333
b1011010 #
b11111010 "
#394003110333
b1011011 #
b11111010 "
#394669782333
b1011100 #
b11111010 "
#395336454333
b1011101 #
b11111010 "
#396003126333
b1011110 #
b11111010 "
#396669798333
b1011111 #
b11111010 "
#397336470333
b1100000 #
b11111010 "
#398003142333
b1100001 #
b11111010 "
#398669814333
b1100010 #
b11111010 "
#399336486333
b1100011 #
b11111010 "
#400003158333
b1100100 #
b11111010 "
#400669830333
b1100101 #
b11111010 "
#401336502333
b1100110 #
b11111010 "
#402003174333
b1100111 #
b11111010 "
#402669846333
b1101000 #
b11111010 "
#403336518333
b1101001 #
b11111010 "
#404003190333
b1101010 #
b11111010 "
#404669862333
b1101011 #
b11111010 "
#405336534333
b1101100 #
b11111010 "
#406003206333
b1101101 #
b11111010 "
#406669878333
b1101110 #
b11111010 "
#407336550333
b1101111 #
b11111010 "
#408003222333
b1110000 #
b11111010 "
#408669894333
b1110001 #
b11111010 "
#409336566333
b1110010 #
b11111010 "
#410003238333
b1110011 #
b11111010 "
#410669910333
b1110100 #
b11111010 "
#411336582333
b1110101 #
b11111010 "
#412003254333
b1110110 #
b11111010 "
#412669926333
b1110111 #
b11111010 "
#413336598333
b1111000 #
b11111010 "
#414003270333
b1111001 #
b11111010 "
#414669942333
b1111010 #
b11111010 "
#415336614333
b1111011 #
b11111010 "
#416003286333
b1111100 #
b11111010 "
#416669958333
b1111101 #
b11111010 "
#417336630333
b1111110 #
b11111010 "
#418003302333
b1111111 #
b11111010 "
#418669974333
b10000000 #
b11111010 "
#419336646333
b10000001 #
b11111010 "
#420003318333
b10000010 #
b11111010 "
#420669990333
b10000011 #
b11111010 "
#421336662333
b10000100 #
b11111010 "
#422003334333
b10000101 #
b11111010 "
#422670006333
b10000110 #
b11111010 "
#423336678333
b10000111 #
b11111010 "
#424003350333
b10001000 #
b11111010 "
#424670022333
b10001001 #
b11111010 "
#425336694333
b10001010 #
b11111010 "
#426003366333
b10001011 #
b11111010 "
#426670038333
b10001100 #
b11111010 "
#427336710333
b10001101 #
b11111010 "
#428003382333
b10001110 #
b11111010 "
#428670054333
b10001111 #
b11111010 "
#429336726333
b10010000 #
b11111010 "
#430003398333
b10010001 #
b11111010 "
#430670070333
b10010010 #
b11111010 "
#431336742333
b10010011 #
b11111010 "
#432003414333
b10010100 #
b11111010 "
#432670086333
b10010101 #
b11111010 "
#433336758333
b10010110 #
b11111010 "
#434003430333
b10010111 #
b11111010 "
#434670102333
b10011000 #
b11111010 "
#435336774333
b10011001 #
b11111010 "
#436003446333
b10011010 #
b11111010 "
#436670118333
b10011011 #
b11111010 "
#437336790333
b10011100 #
b11111010 "
#438003462333
b10011101 #
b11111010 "
#438670134333
b10011110 #
b11111010 "
#439336806333
b10011111 #
b11111010 "
#440003478333
b10100000 #
b11111010 "
#440670150333
b10100001 #
b11111010 "
#441336822333
b10100010 #
b11111010 "
#442003494333
b10100011 #
b11111010 "
#442670166333
b10100100 #
b11111010 "
#443336838333
b10100101 #
b11111010 "
#444003510333
b10100110 #
b11111010 "
#444670182333
b10100111 #
b11111010 "
